{
    "data": {
        "abe": {
            "bitwidth": 9,
            "resources": 256,
            "bitwise_mean": [
                0.969743987587277,
                0.4614041892940264,
                0.3610356865787432,
                0.34193173002327387,
                0.3614235841737781,
                0.4299844840961986,
                0.3763576415826222,
                0.386733902249806,
                0.4078743211792087
            ],
            "bitwise_variance": [
                0.02934058612560696,
                0.24851036339595492,
                0.23068891959535912,
                0.22501442202656716,
                0.23079657697674022,
                0.24509782753269987,
                0.2347125672050117,
                0.23717079110044775,
                0.24151285930181474
            ],
            "total_transitions": 27789.0,
            "total_transitions_per_line": [
                623.0,
                1588.0,
                2888.0,
                3248.0,
                3297.0,
                3829.0,
                3810.0,
                4003.0,
                4503.0
            ],
            "total_samples": 10312,
            "average_sa": 0.2994536579057964,
            "average_sa_per_line": [
                0.06042090970807875,
                0.15401028028319272,
                0.2800892250994084,
                0.3150033944331297,
                0.319755600814664,
                0.3713509843856076,
                0.36950829211521674,
                0.38822616623023953,
                0.4367180680826302
            ]
        }
    },
    "conv1": {
        "abe": {
            "bitwidth": 9,
            "resources": 256,
            "bitwise_mean": [
                0.969743987587277,
                0.006012412723041117,
                0.009891388673390225,
                0.0067882079131109385,
                0.0033941039565554693,
                0.012121799844840962,
                0.03529868114817688,
                0.06322730799069046,
                0.10250193948797517
            ],
            "bitwise_variance": [
                0.02934058612560696,
                0.005976263616289922,
                0.009793549103503319,
                0.006742128146438997,
                0.0033825840148880527,
                0.011974861813361881,
                0.03405268425737603,
                0.05922961551494535,
                0.09199529188919797
            ],
            "total_transitions": 5198.0,
            "total_transitions_per_line": [
                623.0,
                124.0,
                204.0,
                140.0,
                70.0,
                248.0,
                686.0,
                1225.0,
                1878.0
            ],
            "total_samples": 10312,
            "average_sa": 0.056013534628605914,
            "average_sa_per_line": [
                0.06042090970807875,
                0.012025991659392882,
                0.019784695955775384,
                0.013577732518669382,
                0.006788866259334691,
                0.024051983318785764,
                0.06653088934147998,
                0.11880515953835709,
                0.1821355833575793
            ]
        }
    },
    "pool1": {
        "abe": {
            "bitwidth": 9,
            "resources": 256,
            "bitwise_mean": [
                0.969743987587277,
                0.010182311869666408,
                0.011442979053529869,
                0.008145849495733127,
                0.009115593483320403,
                0.048875096974398756,
                0.11966640806826997,
                0.20122187742435996,
                0.24136927851047324
            ],
            "bitwise_variance": [
                0.02934058612560696,
                0.010078632394657644,
                0.0113120372839131,
                0.008079494631726487,
                0.009032499438768622,
                0.04648632187013383,
                0.1053463588482951,
                0.16073163347014188,
                0.1831101499017901
            ],
            "total_transitions": 10560.0,
            "total_transitions_per_line": [
                623.0,
                210.0,
                236.0,
                168.0,
                188.0,
                876.0,
                1918.0,
                2939.0,
                3402.0
            ],
            "total_samples": 10312,
            "average_sa": 0.11379432968027672,
            "average_sa_per_line": [
                0.06042090970807875,
                0.020366598778004074,
                0.022888177674328387,
                0.016293279022403257,
                0.018232955096498884,
                0.08495781204538842,
                0.18601493550577053,
                0.28503539908835224,
                0.329938900203666
            ]
        }
    },
    "norm1": {
        "abe": {
            "bitwidth": 9,
            "resources": 256,
            "bitwise_mean": [
                0.969743987587277,
                0.01095810705973623,
                0.011442979053529869,
                0.007370054305663305,
                0.01095810705973623,
                0.051978277734678044,
                0.12403025601241273,
                0.20374321179208688,
                0.25087276958882854
            ],
            "bitwise_variance": [
                0.02934058612560696,
                0.010838026949405239,
                0.011312037283913426,
                0.0073157366051953086,
                0.010838026949405354,
                0.049276536378410174,
                0.10864675160590309,
                0.16223191544070184,
                0.18793562306764588
            ],
            "total_transitions": 10884.0,
            "total_transitions_per_line": [
                623.0,
                226.0,
                236.0,
                152.0,
                226.0,
                928.0,
                1984.0,
                2983.0,
                3526.0
            ],
            "total_samples": 10312,
            "average_sa": 0.11728574661364885,
            "average_sa_per_line": [
                0.06042090970807875,
                0.021918339637280574,
                0.022888177674328387,
                0.014741538163126757,
                0.021918339637280574,
                0.09000096983803704,
                0.1924158665502861,
                0.28930268645136265,
                0.3419648918630589
            ]
        }
    },
    "conv2": {
        "abe": {
            "bitwidth": 9,
            "resources": 256,
            "bitwise_mean": [
                0.969743987587277,
                0.011830876648564779,
                0.011927851047323506,
                0.005624515128006206,
                0.010667183863460047,
                0.059542280837858806,
                0.13295190069821566,
                0.22304111714507371,
                0.2380721489526765
            ],
            "bitwise_variance": [
                0.02934058612560696,
                0.011690907006293329,
                0.011785577416714101,
                0.00559287995758008,
                0.010553395051881928,
                0.055996997630478135,
                0.11527569279895632,
                0.17329377720775116,
                0.1813938008457408
            ],
            "total_transitions": 12201.0,
            "total_transitions_per_line": [
                623.0,
                244.0,
                246.0,
                116.0,
                204.0,
                1138.0,
                2396.0,
                3570.0,
                3664.0
            ],
            "total_samples": 10312,
            "average_sa": 0.1314777098891152,
            "average_sa_per_line": [
                0.06042090970807875,
                0.023664048103966637,
                0.0238580157113762,
                0.01125012122975463,
                0.019784695955775384,
                0.11036756861604112,
                0.232373193676656,
                0.34623217922606925,
                0.3553486567743187
            ]
        }
    },
    "pool2": {
        "abe": {
            "bitwidth": 9,
            "resources": 256,
            "bitwise_mean": [
                0.969743987587277,
                0.011152055857253686,
                0.012024825446082235,
                0.0074670287044220325,
                0.023370830100853376,
                0.11404189294026378,
                0.2352598913886734,
                0.3144879751745539,
                0.3182699767261443
            ],
            "bitwise_variance": [
                0.02934058612560696,
                0.011027687507411262,
                0.01188022901907148,
                0.0074112721867495585,
                0.022824634401247518,
                0.10103633959484769,
                0.17991267489242263,
                0.2155852886451368,
                0.21697419864085316
            ],
            "total_transitions": 16441.0,
            "total_transitions_per_line": [
                623.0,
                230.0,
                248.0,
                154.0,
                460.0,
                1966.0,
                3717.0,
                4550.0,
                4493.0
            ],
            "total_samples": 10312,
            "average_sa": 0.1771678574122566,
            "average_sa_per_line": [
                0.06042090970807875,
                0.0223062748520997,
                0.024051983318785764,
                0.01493550577053632,
                0.0446125497041994,
                0.19067015808360005,
                0.3604887983706721,
                0.4412763068567549,
                0.4357482300455824
            ]
        }
    },
    "norm2": {
        "abe": {
            "bitwidth": 9,
            "resources": 256,
            "bitwise_mean": [
                0.969743987587277,
                0.012994569433669511,
                0.010376260667183864,
                0.007370054305663305,
                0.027540729247478666,
                0.11947245927075252,
                0.24243599689681924,
                0.31671838634600463,
                0.3207913110938712
            ],
            "bitwise_variance": [
                0.02934058612560696,
                0.012825710598904833,
                0.010268593881752648,
                0.0073157366051949035,
                0.02678223747999045,
                0.1051987907465509,
                0.18366078430549565,
                0.2164078500964293,
                0.21788424582055718
            ],
            "total_transitions": 16747.0,
            "total_transitions_per_line": [
                623.0,
                268.0,
                214.0,
                152.0,
                556.0,
                2052.0,
                3809.0,
                4520.0,
                4553.0
            ],
            "total_samples": 10312,
            "average_sa": 0.18046530673821917,
            "average_sa_per_line": [
                0.06042090970807875,
                0.025991659392881387,
                0.020754533992823197,
                0.014741538163126757,
                0.0539229948598584,
                0.19901076520221123,
                0.369411308311512,
                0.43836679274561147,
                0.44156725826786924
            ]
        }
    },
    "conv3": {
        "abe": {
            "bitwidth": 9,
            "resources": 256,
            "bitwise_mean": [
                0.969743987587277,
                0.0080488750969744,
                0.010279286268425137,
                0.010279286268425137,
                0.0252133436772692,
                0.06875484871993794,
                0.11792086889061287,
                0.13237005430566331,
                0.14158262218774242
            ],
            "bitwise_variance": [
                0.02934058612560696,
                0.007984090706648473,
                0.010173622542236901,
                0.010173622542236901,
                0.024577630977883916,
                0.0640276194974319,
                0.10401553757071395,
                0.11484822302877087,
                0.12153698328217391
            ],
            "total_transitions": 10010.0,
            "total_transitions_per_line": [
                623.0,
                166.0,
                212.0,
                212.0,
                502.0,
                1328.0,
                2111.0,
                2369.0,
                2487.0
            ],
            "total_samples": 10312,
            "average_sa": 0.10786754167609565,
            "average_sa_per_line": [
                0.06042090970807875,
                0.016099311414993697,
                0.020560566385413637,
                0.020560566385413637,
                0.04868586945980021,
                0.12879449131994958,
                0.20473280962079332,
                0.2297546309766269,
                0.2411987198137911
            ]
        }
    },
    "conv4": {
        "abe": {
            "bitwidth": 9,
            "resources": 256,
            "bitwise_mean": [
                0.969743987587277,
                0.009891388673390225,
                0.009891388673390225,
                0.01057020946470132,
                0.05576027928626843,
                0.18502715283165244,
                0.2583397982932506,
                0.2783165244375485,
                0.2903413498836307
            ],
            "bitwise_variance": [
                0.02934058612560696,
                0.0097935491035032,
                0.00979354910350329,
                0.010458480136572195,
                0.05265107054018557,
                0.1507921055466371,
                0.19160034691102024,
                0.20085643666257358,
                0.2060432504314104
            ],
            "total_transitions": 17458.0,
            "total_transitions_per_line": [
                623.0,
                204.0,
                204.0,
                218.0,
                1058.0,
                2991.0,
                3924.0,
                4110.0,
                4126.0
            ],
            "total_samples": 10312,
            "average_sa": 0.1881270272308969,
            "average_sa_per_line": [
                0.06042090970807875,
                0.019784695955775384,
                0.019784695955775384,
                0.021142469207642324,
                0.10260886431965861,
                0.29007855688100087,
                0.3805644457375618,
                0.39860343322665115,
                0.40015517408592766
            ]
        }
    },
    "conv5": {
        "abe": {
            "bitwidth": 9,
            "resources": 256,
            "bitwise_mean": [
                0.969743987587277,
                0.004169899146625291,
                0.008533747090768037,
                0.009115593483320403,
                0.014352211016291699,
                0.03481380915438324,
                0.05799069045771916,
                0.06584561675717611,
                0.07185802948021722
            ],
            "bitwise_variance": [
                0.02934058612560696,
                0.0041525110877324075,
                0.008460922251357552,
                0.009032499438768573,
                0.01414622505523821,
                0.03360180784655225,
                0.05462777027795285,
                0.06150997151104382,
                0.06669445307944993
            ],
            "total_transitions": 5699.0,
            "total_transitions_per_line": [
                623.0,
                86.0,
                176.0,
                188.0,
                288.0,
                668.0,
                1076.0,
                1245.0,
                1349.0
            ],
            "total_samples": 10312,
            "average_sa": 0.061412299701505406,
            "average_sa_per_line": [
                0.06042090970807875,
                0.008340607118611192,
                0.01706914945204151,
                0.018232955096498884,
                0.027931335466977014,
                0.06478518087479392,
                0.10435457278634468,
                0.12074483561245272,
                0.13083115119774996
            ]
        }
    },
    "pool5": {
        "abe": {
            "bitwidth": 9,
            "resources": 256,
            "bitwise_mean": [
                0.969743987587277,
                0.007660977501939488,
                0.010182311869666408,
                0.011539953452288596,
                0.04625678820791311,
                0.08950737005430566,
                0.13033359193173003,
                0.1448797517455392,
                0.15166795965865013
            ],
            "bitwise_variance": [
                0.02934058612560696,
                0.007602286925654972,
                0.010078632394657783,
                0.011406782926609774,
                0.04411709775259526,
                0.08149580076024995,
                0.11334674674588176,
                0.12388960927970696,
                0.12866478967162914
            ],
            "total_transitions": 11088.0,
            "total_transitions_per_line": [
                623.0,
                158.0,
                210.0,
                238.0,
                884.0,
                1628.0,
                2267.0,
                2489.0,
                2591.0
            ],
            "total_samples": 10312,
            "average_sa": 0.11948404616429056,
            "average_sa_per_line": [
                0.06042090970807875,
                0.015323440985355445,
                0.020366598778004074,
                0.02308214528173795,
                0.08573368247502668,
                0.15788963243138396,
                0.21986228299873922,
                0.24139268742120065,
                0.25128503539908836
            ]
        }
    },
    "fc6": {
        "abe": {
            "bitwidth": 9,
            "resources": 256,
            "bitwise_mean": [
                0.969743987587277,
                0.0064003103180760275,
                0.009309542280837859,
                0.05188130333591932,
                0.09968968192397207,
                0.12451512800620636,
                0.13149728471683475,
                0.13372769588828548,
                0.1383824670287044
            ],
            "bitwise_variance": [
                0.02934058612560696,
                0.006359346345908738,
                0.009222874703358025,
                0.049189633700092855,
                0.08975164924188773,
                0.10901111090381296,
                0.11420574882893562,
                0.115844599240697,
                0.11923275984776646
            ],
            "total_transitions": 13199.0,
            "total_transitions_per_line": [
                623.0,
                132.0,
                190.0,
                1008.0,
                1820.0,
                2254.0,
                2344.0,
                2380.0,
                2448.0
            ],
            "total_samples": 10312,
            "average_sa": 0.1422321361221565,
            "average_sa_per_line": [
                0.06042090970807875,
                0.012801862089031132,
                0.018426922703908447,
                0.09775967413441955,
                0.17651052274270196,
                0.21860149355057706,
                0.22733003588400738,
                0.2308214528173795,
                0.23741635146930462
            ]
        }
    },
    "fc7": {
        "abe": {
            "bitwidth": 9,
            "resources": 256,
            "bitwise_mean": [
                0.969743987587277,
                0.008727695888285493,
                0.013188518231186967,
                0.09416214119472459,
                0.17726920093095422,
                0.20219162141194724,
                0.21925911559348332,
                0.22614429790535298,
                0.2373933281613654
            ],
            "bitwise_variance": [
                0.02934058612560696,
                0.008651523212768285,
                0.013014581218051088,
                0.08529563236033398,
                0.14584483133223164,
                0.16131016964273817,
                0.17118455582265443,
                0.17500305443023098,
                0.1810377359058651
            ],
            "total_transitions": 19911.0,
            "total_transitions_per_line": [
                623.0,
                180.0,
                272.0,
                1738.0,
                2962.0,
                3272.0,
                3513.0,
                3644.0,
                3707.0
            ],
            "total_samples": 10312,
            "average_sa": 0.2145605017295445,
            "average_sa_per_line": [
                0.06042090970807875,
                0.017457084666860634,
                0.026379594607700514,
                0.1685578508389099,
                0.2872660265735622,
                0.3173310057220444,
                0.34070410241489674,
                0.3534089807002231,
                0.3595189603336243
            ]
        }
    },
    "fc8_sbt": {
        "abe": {
            "bitwidth": 9,
            "resources": 256,
            "bitwise_mean": [
                0.9696969696969697,
                0.41818181818181815,
                0.3,
                0.41515151515151516,
                0.46060606060606063,
                0.40606060606060607,
                0.37575757575757573,
                0.3393939393939394,
                0.45151515151515154
            ],
            "bitwise_variance": [
                0.029384756657483954,
                0.2433057851239663,
                0.2100000000000014,
                0.24280073461891583,
                0.24844811753902774,
                0.24117539026629917,
                0.2345638200183653,
                0.22420569329660242,
                0.24764921946740054
            ],
            "total_transitions": 1042.0,
            "total_transitions_per_line": [
                19.0,
                117.0,
                112.0,
                132.0,
                141.0,
                146.0,
                132.0,
                98.0,
                145.0
            ],
            "total_samples": 330,
            "average_sa": 0.3519081391421817,
            "average_sa_per_line": [
                0.057750759878419454,
                0.3556231003039514,
                0.3404255319148936,
                0.4012158054711246,
                0.42857142857142855,
                0.44376899696048633,
                0.4012158054711246,
                0.2978723404255319,
                0.44072948328267475
            ]
        }
    },
    "prob": {
        "abe": {
            "bitwidth": 9,
            "resources": 256,
            "bitwise_mean": [
                0.9696969696969697,
                0.0030303030303030303,
                0.1787878787878788,
                0.15454545454545454,
                0.12727272727272726,
                0.19393939393939394,
                0.2515151515151515,
                0.29393939393939394,
                0.2787878787878788
            ],
            "bitwise_variance": [
                0.029384756657483954,
                0.0030211202938475634,
                0.14682277318641015,
                0.13066115702479256,
                0.11107438016528913,
                0.15632690541781472,
                0.1882552800734612,
                0.20753902662993592,
                0.2010651974288327
            ],
            "total_transitions": 750.0,
            "total_transitions_per_line": [
                19.0,
                2.0,
                118.0,
                96.0,
                66.0,
                94.0,
                120.0,
                117.0,
                118.0
            ],
            "total_samples": 330,
            "average_sa": 0.25329280648429586,
            "average_sa_per_line": [
                0.057750759878419454,
                0.0060790273556231,
                0.3586626139817629,
                0.2917933130699088,
                0.2006079027355623,
                0.2857142857142857,
                0.364741641337386,
                0.3556231003039514,
                0.3586626139817629
            ]
        }
    }
}